odoo10_addon_purchase_request_to_procurement-10.0.1.0.0.99.dev15-py3.8-nspkg.pth
odoo/addons/purchase_request_to_procurement/README.rst
odoo/addons/purchase_request_to_procurement/__init__.py
odoo/addons/purchase_request_to_procurement/__manifest__.py
odoo/addons/purchase_request_to_procurement/i18n/am.po
odoo/addons/purchase_request_to_procurement/i18n/ar.po
odoo/addons/purchase_request_to_procurement/i18n/bg.po
odoo/addons/purchase_request_to_procurement/i18n/bs.po
odoo/addons/purchase_request_to_procurement/i18n/ca.po
odoo/addons/purchase_request_to_procurement/i18n/cs.po
odoo/addons/purchase_request_to_procurement/i18n/da.po
odoo/addons/purchase_request_to_procurement/i18n/de.po
odoo/addons/purchase_request_to_procurement/i18n/el_GR.po
odoo/addons/purchase_request_to_procurement/i18n/en_GB.po
odoo/addons/purchase_request_to_procurement/i18n/es.po
odoo/addons/purchase_request_to_procurement/i18n/es_AR.po
odoo/addons/purchase_request_to_procurement/i18n/es_CO.po
odoo/addons/purchase_request_to_procurement/i18n/es_CR.po
odoo/addons/purchase_request_to_procurement/i18n/es_DO.po
odoo/addons/purchase_request_to_procurement/i18n/es_EC.po
odoo/addons/purchase_request_to_procurement/i18n/es_ES.po
odoo/addons/purchase_request_to_procurement/i18n/es_MX.po
odoo/addons/purchase_request_to_procurement/i18n/es_PE.po
odoo/addons/purchase_request_to_procurement/i18n/es_PY.po
odoo/addons/purchase_request_to_procurement/i18n/es_VE.po
odoo/addons/purchase_request_to_procurement/i18n/et.po
odoo/addons/purchase_request_to_procurement/i18n/eu.po
odoo/addons/purchase_request_to_procurement/i18n/fa.po
odoo/addons/purchase_request_to_procurement/i18n/fi.po
odoo/addons/purchase_request_to_procurement/i18n/fr.po
odoo/addons/purchase_request_to_procurement/i18n/fr_BE.po
odoo/addons/purchase_request_to_procurement/i18n/fr_CA.po
odoo/addons/purchase_request_to_procurement/i18n/fr_CH.po
odoo/addons/purchase_request_to_procurement/i18n/gl.po
odoo10_addon_purchase_request_to_procurement-10.0.1.0.0.99.dev15.dist-info/METADATA
odoo10_addon_purchase_request_to_procurement-10.0.1.0.0.99.dev15.dist-info/WHEEL
odoo10_addon_purchase_request_to_procurement-10.0.1.0.0.99.dev15.dist-info/namespace_packages.txt
odoo10_addon_purchase_request_to_procurement-10.0.1.0.0.99.dev15.dist-info/top_level.txt
odoo10_addon_purchase_request_to_procurement-10.0.1.0.0.99.dev15.dist-info/RECORD
